[
    {
        "type": "readers.las",
        "filename": "/home/juju/geodata/lidar/niederanven_grunewald/*.laz"
    },
    {
        "type": "filters.range",
        "limits": "Classification[2:2]"
    },
    {
        "type": "writers.gdal",
        "filename": "/home/juju/orienteering/niederanven_grunewald/dtm.tif",
        "output_type": "min",
        "resolution": 0.25,
        "data_type": "float32",
        "gdaldriver": "GTiff",
        "window_size": 1,
        "radius": 0.25
    }
]
